novum_api_client/__init__.py
novum_api_client/api_type.py
novum_api_client/base_client.py
novum_api_client/client.py
novum_api_client/tests/__init__.py
novum_api_client/tests/test_api_base.py
novum_api_client/tests/test_api_public.py
novum_api_client-3.0.0.dist-info/LICENSE
novum_api_client-3.0.0.dist-info/METADATA
novum_api_client-3.0.0.dist-info/WHEEL
novum_api_client-3.0.0.dist-info/RECORD
