Metadata-Version: 2.1
Name: novum_api_client
Version: 3.0.0
Summary: This library contains the basic api functions for Novum Service Center.
License: MIT
Author: Leonardo
Author-email: l.biz@novum-engineering.com
Requires-Python: >=3.8.1,<4.0.0
Classifier: License :: OSI Approved :: MIT License
Classifier: Programming Language :: Python :: 3
Classifier: Programming Language :: Python :: 3.9
Classifier: Programming Language :: Python :: 3.10
Classifier: Programming Language :: Python :: 3.11
Classifier: Programming Language :: Python :: 3.12
Requires-Dist: dataclasses-json (>=0.6.3,<0.7.0)
Requires-Dist: requests (>=2.28.2,<3.0.0)
